Metadata-Version: 2.1
Name: chatoperastore
Version: 1.2.0
Summary: Chatopera Store SDK for Python, Chatopera 证书商店 Python SDK, 实现软件中付费资源的证书管理，比如检查配额、证书验证、续费管理等
Home-page: https://store.chatopera.com
Author: Hai Liang Wang
Author-email: hain@chatopera.com
License: Chunsong Public License, version 1.0
Keywords: billing,invoice,payment,license
Platform: UNKNOWN
Classifier: Intended Audience :: Developers
Classifier: Operating System :: OS Independent
Classifier: Natural Language :: Chinese (Simplified)
Classifier: Natural Language :: Chinese (Traditional)
Classifier: Programming Language :: Python
Classifier: Programming Language :: Python :: 2
Classifier: Programming Language :: Python :: 2.7
Classifier: Programming Language :: Python :: 3
Classifier: Programming Language :: Python :: 3.5
Classifier: Programming Language :: Python :: 3.6
Classifier: Programming Language :: Python :: 3.7
